rc4/__init__.py
rc4/rc4.py
rc4_python3-1.1.5.dist-info/METADATA
rc4_python3-1.1.5.dist-info/WHEEL
rc4_python3-1.1.5.dist-info/entry_points.txt
rc4_python3-1.1.5.dist-info/top_level.txt
rc4_python3-1.1.5.dist-info/RECORD
